Data/__init__.py
Data/preprocess_data.py
Energy_Models/Autoformer.py
Energy_Models/BiGRU.py
Energy_Models/BiLSTM.py
Energy_Models/CNN.py
Energy_Models/CNN_LSTM.py
Energy_Models/ConvLstm.py
Energy_Models/DeepAr.py
Energy_Models/Evaluation_Metrix.py
Energy_Models/FNN.py
Energy_Models/GRU.py
Energy_Models/Informer.py
Energy_Models/LSTM.py
Energy_Models/LstNet.py
Energy_Models/MLP.py
Energy_Models/NBEATS.py
Energy_Models/Performer.py
Energy_Models/RBFN.py
Energy_Models/Seq2Seq.py
Energy_Models/TCN.py
Energy_Models/TimeDistributed.py
Energy_Models/Transformer.py
Energy_Models/__init__.py
Energy_Models/bert.py
EnergyModels-0.0.9.dist-info/LICENSE
EnergyModels-0.0.9.dist-info/METADATA
EnergyModels-0.0.9.dist-info/WHEEL
EnergyModels-0.0.9.dist-info/top_level.txt
EnergyModels-0.0.9.dist-info/RECORD
